wixok/__init__.py
wixok/txttoolkit/__init__.py
wixok/txttoolkit/txttoolkit.py
wixok_txttoolkit-25.8.3.dist-info/METADATA
wixok_txttoolkit-25.8.3.dist-info/WHEEL
wixok_txttoolkit-25.8.3.dist-info/entry_points.txt
wixok_txttoolkit-25.8.3.dist-info/top_level.txt
wixok_txttoolkit-25.8.3.dist-info/RECORD
