Metadata-Version: 2.4
Name: wixok.txttoolkit
Version: 25.8.3
Summary: Simple Python utility for text file operations.
Author-email: Wixok <contact@wixok.com>
Maintainer-email: Mohammed Dellihr <mohammeddellihr@maildoo.com>
Project-URL: Homepage, https://txttoolkit.wixok.com
Project-URL: Repository, https://github.com/wixok/txttoolkit
Project-URL: Issues, https://github.com/wixok/txttoolkit/issues
Keywords: text,file,io,toolkit,txttoolkit
Classifier: Development Status :: 5 - Production/Stable
Classifier: Intended Audience :: Developers
Classifier: License :: OSI Approved :: MIT License
Classifier: Programming Language :: Python :: 3
Classifier: Programming Language :: Python :: 3.8
Classifier: Programming Language :: Python :: 3.9
Classifier: Programming Language :: Python :: 3.10
Classifier: Programming Language :: Python :: 3.11
Classifier: Programming Language :: Python :: 3.12
Requires-Python: >=3.8
Provides-Extra: dev
Requires-Dist: pytest>=7.0; extra == "dev"
Requires-Dist: black; extra == "dev"
Requires-Dist: mypy; extra == "dev"
Provides-Extra: docs
Requires-Dist: mkdocs; extra == "docs"
Requires-Dist: mkdocs-material; extra == "docs"
